grz_common/__init__.py
grz_common/constants.py
grz_common/logging.py
grz_common/py.typed
grz_common/transfer.py
grz_common/cli/__init__.py
grz_common/models/__init__.py
grz_common/models/base.py
grz_common/models/identifiers.py
grz_common/models/keys.py
grz_common/models/s3.py
grz_common/progress/__init__.py
grz_common/progress/progress_logging.py
grz_common/progress/states.py
grz_common/utils/__init__.py
grz_common/utils/checksums.py
grz_common/utils/crypt.py
grz_common/utils/io.py
grz_common/utils/paths.py
grz_common/validation/__init__.py
grz_common/validation/bam.py
grz_common/validation/fastq.py
grz_common/workers/__init__.py
grz_common/workers/download.py
grz_common/workers/submission.py
grz_common/workers/upload.py
grz_common/workers/worker.py
grz_common-1.6.1.dist-info/METADATA
grz_common-1.6.1.dist-info/WHEEL
grz_common-1.6.1.dist-info/RECORD
